{
  "activeBrandingSetId" : "4d375cea-f0bc-4b63-a97c-b12f06effd4f",
  "customCSS" : "@font-face {\n    font-family: 'poppins';\n        src: url('/sfsites/c/resource/LWCResource/font/Poppins/Poppins-Medium.ttf') format('truetype');\n}\n\n@font-face {\n    font-family: 'poppins-bold';\n        src: url('/sfsites/c/resource/LWCResource/font/Poppins/Poppins-Bold.ttf') format('truetype');\n}\n\nbody .forceCommunitySection .cb-section_column:first-child {\n    padding: 0;\n}\n\nbody .forceCommunitySection .cb-section_column:first-child {\n    border-right: 2px solid #FF7570;\n      min-height: 100vh;\n}\n\nbody, html {\n    min-height: 100vh;\n   overflow: auto;\n}\n\n.slds-form-element__label {\n color: #656565;\n   font-size: 15px;\n }\n\n.slds-form-element__static { \n    color: #3B4EB0;\n    font-size: 17px; \n    font-weight: 600;\n}\n\n.slds-button_brand {\n  background-color: #3B4EB0;\n    font-size: 16px;\n    padding: 6px 20px 6px 20px;\n}\n\n.slds-button_brand:hover {\n    background-color: #1028a5;\n}\n\n.slds-input {\n     background: #F8F8F8;\n     border: 1px solid rgb(233, 233, 233);\n    border-radius: 4px;\n    color: #000;\n    font-size: 16px;\n    font-weight: 700;\n    padding: 9px;\n}",
  "developerName" : "jepson",
  "id" : "45512a29-2484-4d3c-8f1b-5e62f2679335",
  "label" : "Jepson",
  "layouts" : {
    "4pgtGzLuFawvm1YU8yq28ieBomrxUw" : "7d5a3228-0b89-427f-88a6-5269697561ce",
    "Home" : "8fdd1a5a-b178-45de-9aff-3192e6b7cad6",
    "Inner" : "60e08a81-692b-4f0a-ae67-5f5a15f56b6d",
    "Login" : "02a219f5-d9f5-4b7a-8205-673e4f639521",
    "ServiceNotAvailable" : "7680c317-52eb-4328-8005-fdd314535275"
  },
  "type": "theme",
  "views": [
    {
      "componentAttributes": {},
      "componentName": "salesforceIdentity:loginBody2",
      "id": "02a219f5-d9f5-4b7a-8205-673e4f639521",
      "label": "Login",
      "regions": [
        {
          "id": "108dcfac-1d97-4e06-b748-33c4337c37fd",
          "regionName": "header",
          "type": "region"
        },
        {
          "id": "7923ca08-2b48-417c-a630-33664e7e1891",
          "regionName": "content",
          "type": "region"
        },
        {
          "id": "64b52405-7725-4dc6-9f55-de14ef9e33ce",
          "regionName": "footer",
          "type": "region"
        }
      ],
      "type": "view"
    },
    {
      "componentAttributes": {
        "fixedPageWidth": 1440,
        "headerBgColor": "rgba(255, 255, 255, 0.8)",
        "isHeaderPinned": true,
        "isHeroUnderHeader": false,
        "isPageWidthFixed": false,
        "showHeader": true,
        "showHero": false
      },
      "componentName": "siteforce:themeLayoutStarter",
      "id": "60e08a81-692b-4f0a-ae67-5f5a15f56b6d",
      "label": "Default",
      "regions": [
        {
          "components": [
            {
              "componentAttributes": {
                "background": "background: #FFFFFF",
                "backgroundOverlayColor": "rgba(0, 0, 0, 0.3)",
                "borderBottomColor": "rgba(0, 0, 0, 0.5)",
                "centerAlignLogo": false,
                "collapseNavMenu": false,
                "containHeader": false,
                "containHeaderWidth": 1440,
                "dropdownBackgroundColor": "#FFFFFF",
                "dropdownBackgroundHoverColor": "",
                "dropdownBorderColor": "#F0F0F0",
                "dropdownTextColor": "",
                "dropdownTextHoverColor": "",
                "headerHeight": 16,
                "linkActiveBorderColor": "",
                "linkColor": "rgba(0, 0, 0, 0.8)",
                "linkHoverColor": "rgba(0, 0, 0, 0.7)",
                "linkTextShadowColor": "rgba(255, 255, 255, 0)",
                "logoWidth": 150,
                "searchStyle": "expanded",
                "showAppLauncher": false,
                "showNavMenuOnLeft": true,
                "showNotifications": true,
                "showProfileMenu": true,
                "showSearch": true
              },
              "componentName": "forceCommunity:themeHeaderCompact",
              "id": "f0c31d97-d13e-4cdc-b5cb-b59753272368",
              "regions": [
                {
                  "components": [
                    {
                      "componentAttributes": {
                        "buttonBackgroundColor": "",
                        "buttonBackgroundHoverColor": "",
                        "buttonBorderColor": "rgba(0, 0, 0, 0)",
                        "buttonBorderRadius": 15,
                        "buttonText": "Log in",
                        "buttonTextColor": "",
                        "buttonTextHoverColor": "",
                        "customizableUserProfileMenuEditor": "Default_User_Profile_Menu",
                        "menuStyleSettings": "{\"selectedMenuStyleSetting\":\"iconOnly\",\"selectedIconSetting\":\"userAvatar\",\"includeCompanyName\":false,\"selectedTextOrientationSetting\":\"right\"}"
                      },
                      "componentName": "forceCommunity:customizableUserProfileMenu",
                      "id": "eff9e662-3914-4cce-8f6b-bc39c1c66cea",
                      "renditionMap": {},
                      "type": "component"
                    }
                  ],
                  "id": "c8e47f34-0c2f-4bc4-a56b-22579970b48a",
                  "regionName": "themeHeaderProfileMenu",
                  "type": "region"
                },
                {
                  "components": [
                    {
                      "componentAttributes": {
                        "backgroundColor": "#FFFFFF",
                        "borderColor": "rgba(0, 0, 0, 0.8)",
                        "borderRadius": 20,
                        "borderStyle": "outline",
                        "buttonColor": "",
                        "buttonHoverColor": "",
                        "crossObjectTypeaheadApiNames": "",
                        "iconColor": "rgba(0, 0, 0, 0.8)",
                        "placeholderText": "Search...",
                        "placeholderTextColor": "rgba(0, 0, 0, 0.6)",
                        "showSearchButton": false,
                        "textColor": "rgba(0, 0, 0, 0.8)",
                        "typeaheadResultMax": 5,
                        "useTypeahead": true
                      },
                      "componentName": "forceCommunity:themeSearch",
                      "id": "e926f05d-9f3d-4017-b90c-e06b1cde4fe7",
                      "renditionMap": {},
                      "type": "component"
                    }
                  ],
                  "id": "be8abac2-a352-452a-96c9-86fcb5e4c6b3",
                  "regionName": "search",
                  "type": "region"
                },
                {
                  "id": "3b60c4de-4d43-431a-b7f2-55c5fccb0037",
                  "regionName": "nav",
                  "type": "region"
                },
                {
                  "id": "1a55ee8f-5c3e-4d66-9f69-45ada087a491",
                  "regionName": "cartIcon",
                  "type": "region"
                }
              ],
              "renditionMap": {},
              "type": "component"
            }
          ],
          "id": "f0d3014a-f4dc-4489-af80-7b59d5742d50",
          "regionName": "themeHeader",
          "type": "region"
        },
        {
          "components": [
            {
              "componentAttributes": {
                "bgImage": "background: #FFFFFF url(/sfsites/assets/themes/jepson-background.jpg) top center /cover",
                "bgOverlayColor": "rgba(255, 255, 255, 0.20)",
                "captionText": "Our Mission",
                "captionTextColor": "rgba(0, 0, 0, 0.8)",
                "captionTextShadowColor": "rgba(0, 0, 0, 0)",
                "contentAlignment": "right",
                "contentWidth": 45,
                "ctaBtnOneBgColor": "",
                "ctaBtnOneBgHoverColor": "",
                "ctaBtnOneBorderColor": "rgba(10, 50, 198, 0)",
                "ctaBtnOneOpenNewTab": false,
                "ctaBtnOneText": "Our Projects",
                "ctaBtnOneTextColor": "",
                "ctaBtnOneTextHoverColor": "",
                "ctaBtnOneUrl": "",
                "ctaBtnRadius": 25,
                "ctaBtnTwoBgColor": "rgba(255, 255, 255, 0)",
                "ctaBtnTwoBgHoverColor": "rgba(255, 255, 255, 0.9)",
                "ctaBtnTwoBorderColor": "rgba(0, 0, 0, 0.8)",
                "ctaBtnTwoOpenNewTab": false,
                "ctaBtnTwoText": "Contact Us",
                "ctaBtnTwoTextColor": "rgba(0, 0, 0, 0.8)",
                "ctaBtnTwoTextHoverColor": "rgba(0, 0, 0, 0.8)",
                "ctaBtnTwoUrl": "",
                "ctaShowBtnOne": true,
                "ctaShowBtnTwo": true,
                "fixedHeroWidth": true,
                "heroHeight": 162,
                "heroWidth": 1440,
                "showCaption": true,
                "showSubtitle": true,
                "showTitle": true,
                "subtitleText": "We specialize in the construction of unique and exclusive properties.  We deliver outstanding quality and design for leading architects and private clients around the world.",
                "subtitleTextColor": "rgba(0, 0, 0, 0.8)",
                "subtitleTextShadowColor": "rgba(0, 0, 0, 0)",
                "titleText": "Your Dream Home",
                "titleTextColor": "rgba(0, 0, 0, 0.8)",
                "titleTextShadowColor": "rgba(0, 0, 0, 0)",
                "type": "callToAction"
              },
              "componentName": "forceCommunity:themeHeroStarter",
              "id": "f61625c9-c5f2-49f9-8d99-1aceb203f5ed",
              "regions": [
                {
                  "components": [
                    {
                      "componentAttributes": {
                        "backgroundColor": "#FFFFFF",
                        "borderColor": "rgba(0, 0, 0, 0)",
                        "borderRadius": 25,
                        "borderStyle": "outline",
                        "buttonColor": "",
                        "buttonHoverColor": "",
                        "crossObjectTypeaheadApiNames": "",
                        "iconColor": "#FFFFFF",
                        "placeholderText": "Ask a question...",
                        "placeholderTextColor": "rgba(0, 0, 0, 0.6)",
                        "publicDropdownBackgroundColor": "#FFFFFF",
                        "publicDropdownBackgroundHoverColor": "",
                        "publicDropdownBorderColor": "#F0F0F0",
                        "publicDropdownTextColor": "",
                        "publicDropdownTextHoverColor": "",
                        "showSearchButton": true,
                        "textColor": "rgba(0, 0, 0, 0.8)",
                        "typeaheadResultMax": 6,
                        "useTypeahead": true
                      },
                      "componentName": "forceCommunity:themeSearchHero",
                      "id": "67429f9f-7fe6-4819-b426-e21d9f686607",
                      "renditionMap": {},
                      "type": "component"
                    }
                  ],
                  "id": "582eeac0-159e-4430-9dd7-7e46d5078a3e",
                  "regionName": "search",
                  "type": "region"
                }
              ],
              "renditionMap": {},
              "type": "component"
            }
          ],
          "id": "bcdafb9c-7d5b-4cf3-9cab-0197ae118638",
          "regionName": "themeHero",
          "type": "region"
        },
        {
          "id": "97621427-695b-43a6-b78f-e3eb315f1d50",
          "regionName": "themeFooter",
          "type": "region"
        }
      ],
      "type": "view"
    },
    {
      "componentAttributes": {
        "fixedPageWidth": 1440,
        "headerBgColor": "rgba(255, 255, 255, 0.8)",
        "isHeaderPinned": false,
        "isHeroUnderHeader": false,
        "isPageWidthFixed": false,
        "showHeader": true,
        "showHero": false
      },
      "componentName": "siteforce:themeLayoutStarter",
      "id": "8fdd1a5a-b178-45de-9aff-3192e6b7cad6",
      "label": "Home",
      "regions": [
        {
          "components": [
            {
              "componentAttributes": {
                "background": "background: #FFFFFF",
                "backgroundOverlayColor": "rgba(0, 0, 0, 0.3)",
                "borderBottomColor": "rgba(0, 0, 0, 0.5)",
                "centerAlignLogo": false,
                "collapseNavMenu": false,
                "containHeader": false,
                "containHeaderWidth": 1440,
                "dropdownBackgroundColor": "#FFFFFF",
                "dropdownBackgroundHoverColor": "",
                "dropdownBorderColor": "#F0F0F0",
                "dropdownTextColor": "",
                "dropdownTextHoverColor": "",
                "headerHeight": 16,
                "linkActiveBorderColor": "",
                "linkColor": "rgba(0, 0, 0, 0.8)",
                "linkHoverColor": "rgba(0, 0, 0, 0.7)",
                "linkTextShadowColor": "rgba(255, 255, 255, 0)",
                "logoWidth": 150,
                "searchStyle": "expanded",
                "showAppLauncher": false,
                "showNavMenuOnLeft": true,
                "showNotifications": true,
                "showProfileMenu": true,
                "showSearch": false
              },
              "componentName": "forceCommunity:themeHeaderCompact",
              "id": "0d5e0c11-78cb-4432-87a9-866e62ae5cf8",
              "regions": [
                {
                  "components": [
                    {
                      "componentAttributes": {
                        "buttonBackgroundColor": "",
                        "buttonBackgroundHoverColor": "",
                        "buttonBorderColor": "rgba(0, 0, 0, 0)",
                        "buttonBorderRadius": 15,
                        "buttonText": "Log in",
                        "buttonTextColor": "",
                        "buttonTextHoverColor": "",
                        "customizableUserProfileMenuEditor": "Default_User_Profile_Menu",
                        "menuStyleSettings": "{\"selectedMenuStyleSetting\":\"iconOnly\",\"selectedIconSetting\":\"userAvatar\",\"includeCompanyName\":false,\"selectedTextOrientationSetting\":\"right\"}"
                      },
                      "componentName": "forceCommunity:customizableUserProfileMenu",
                      "id": "0efe8ada-30f4-45af-a215-26ce23993afc",
                      "renditionMap": {},
                      "type": "component"
                    }
                  ],
                  "id": "1696c0a1-b9e8-40b6-84fc-cfae67a9a7c6",
                  "regionName": "themeHeaderProfileMenu",
                  "type": "region"
                },
                {
                  "components": [
                    {
                      "componentAttributes": {
                        "backgroundColor": "#FFFFFF",
                        "borderColor": "rgba(0, 0, 0, 0.8)",
                        "borderRadius": 20,
                        "borderStyle": "outline",
                        "buttonColor": "",
                        "buttonHoverColor": "",
                        "crossObjectTypeaheadApiNames": "",
                        "iconColor": "rgba(0, 0, 0, 0.8)",
                        "placeholderText": "Search...",
                        "placeholderTextColor": "rgba(0, 0, 0, 0.6)",
                        "showSearchButton": false,
                        "textColor": "rgba(0, 0, 0, 0.8)",
                        "typeaheadResultMax": 5,
                        "useTypeahead": true
                      },
                      "componentName": "forceCommunity:themeSearch",
                      "id": "127e48bf-bde6-452b-b351-e55560bf8f0e",
                      "renditionMap": {},
                      "type": "component"
                    }
                  ],
                  "id": "fa9e6bfb-faa9-429e-8575-5fec483395b4",
                  "regionName": "search",
                  "type": "region"
                },
                {
                  "id": "5f47fd14-92eb-4c03-bdfc-d90caaf028de",
                  "regionName": "nav",
                  "type": "region"
                },
                {
                  "id": "05f504fe-f505-4cbb-a809-8a0d876e766d",
                  "regionName": "cartIcon",
                  "type": "region"
                }
              ],
              "renditionMap": {},
              "type": "component"
            }
          ],
          "id": "dd844030-02b0-48e6-9fb7-8ea5e59a76eb",
          "regionName": "themeHeader",
          "type": "region"
        },
        {
          "components": [
            {
              "componentAttributes": {
                "bgImage": "background: #FFFFFF url(/sfsites/assets/themes/jepson-background.jpg) top center /cover",
                "bgOverlayColor": "rgba(255, 255, 255, 0.20)",
                "captionText": "Our Mission",
                "captionTextColor": "rgba(0, 0, 0, 0.8)",
                "captionTextShadowColor": "rgba(0, 0, 0, 0)",
                "contentAlignment": "right",
                "contentWidth": 45,
                "ctaBtnOneBgColor": "",
                "ctaBtnOneBgHoverColor": "",
                "ctaBtnOneBorderColor": "rgba(10, 50, 198, 0)",
                "ctaBtnOneOpenNewTab": false,
                "ctaBtnOneText": "Our Projects",
                "ctaBtnOneTextColor": "",
                "ctaBtnOneTextHoverColor": "",
                "ctaBtnOneUrl": "",
                "ctaBtnRadius": 25,
                "ctaBtnTwoBgColor": "rgba(255, 255, 255, 0)",
                "ctaBtnTwoBgHoverColor": "rgba(255, 255, 255, 0.9)",
                "ctaBtnTwoBorderColor": "rgba(0, 0, 0, 0.8)",
                "ctaBtnTwoOpenNewTab": false,
                "ctaBtnTwoText": "Contact Us",
                "ctaBtnTwoTextColor": "rgba(0, 0, 0, 0.8)",
                "ctaBtnTwoTextHoverColor": "rgba(0, 0, 0, 0.8)",
                "ctaBtnTwoUrl": "",
                "ctaShowBtnOne": true,
                "ctaShowBtnTwo": true,
                "fixedHeroWidth": true,
                "heroHeight": 162,
                "heroWidth": 1440,
                "showCaption": true,
                "showSubtitle": true,
                "showTitle": true,
                "subtitleText": "We specialize in the construction of unique and exclusive properties.  We deliver outstanding quality and design for leading architects and private clients around the world.",
                "subtitleTextColor": "rgba(0, 0, 0, 0.8)",
                "subtitleTextShadowColor": "rgba(0, 0, 0, 0)",
                "titleText": "Your Dream Home",
                "titleTextColor": "rgba(0, 0, 0, 0.8)",
                "titleTextShadowColor": "rgba(0, 0, 0, 0)",
                "type": "callToAction"
              },
              "componentName": "forceCommunity:themeHeroStarter",
              "id": "8de126b1-8444-46a1-9e6a-cfc81a0620bf",
              "regions": [
                {
                  "components": [
                    {
                      "componentAttributes": {
                        "backgroundColor": "#FFFFFF",
                        "borderColor": "rgba(0, 0, 0, 0)",
                        "borderRadius": 25,
                        "borderStyle": "outline",
                        "buttonColor": "",
                        "buttonHoverColor": "",
                        "crossObjectTypeaheadApiNames": "",
                        "iconColor": "#FFFFFF",
                        "placeholderText": "Ask a question...",
                        "placeholderTextColor": "rgba(0, 0, 0, 0.6)",
                        "publicDropdownBackgroundColor": "#FFFFFF",
                        "publicDropdownBackgroundHoverColor": "",
                        "publicDropdownBorderColor": "#F0F0F0",
                        "publicDropdownTextColor": "",
                        "publicDropdownTextHoverColor": "",
                        "showSearchButton": true,
                        "textColor": "rgba(0, 0, 0, 0.8)",
                        "typeaheadResultMax": 6,
                        "useTypeahead": true
                      },
                      "componentName": "forceCommunity:themeSearchHero",
                      "id": "9aa565e9-1e44-4449-af84-4fe1d2a4128d",
                      "renditionMap": {},
                      "type": "component"
                    }
                  ],
                  "id": "3bf00215-9699-4b45-88a1-65094de4872e",
                  "regionName": "search",
                  "type": "region"
                }
              ],
              "renditionMap": {},
              "type": "component"
            }
          ],
          "id": "71150ac6-58b0-4ebd-9143-8ee174212cf8",
          "regionName": "themeHero",
          "type": "region"
        },
        {
          "id": "b32bf2c4-2c85-497b-ac7c-d8ec4c77313b",
          "regionName": "themeFooter",
          "type": "region"
        }
      ],
      "type": "view"
    },
    {
      "componentAttributes": {
        "fixedPageWidth": 1440,
        "headerBgColor": "rgba(0, 0, 0, 0)",
        "isHeaderPinned": false,
        "isHeroUnderHeader": false,
        "isPageWidthFixed": false,
        "showHeader": true,
        "showHero": false
      },
      "componentName": "siteforce:themeLayoutStarter",
      "id": "7680c317-52eb-4328-8005-fdd314535275",
      "label": "ServiceNotAvailable",
      "regions": [
        {
          "id": "7ee19cf2-92b8-4b1e-8c3a-6de143f9c917",
          "regionName": "themeHeader",
          "type": "region"
        },
        {
          "id": "fd2618fd-7276-4074-b9b7-011411613d95",
          "regionName": "themeFooter",
          "type": "region"
        }
      ],
      "type": "view"
    },
    {
      "componentAttributes": {
        "fixedPageWidth": 1440,
        "headerBgColor": "rgba(255, 255, 255, 0.8)",
        "isHeaderPinned": false,
        "isHeroUnderHeader": false,
        "isPageWidthFixed": false,
        "showHeader": true,
        "showHero": false
      },
      "componentName": "siteforce:themeLayoutStarter",
      "id": "7d5a3228-0b89-427f-88a6-5269697561ce",
      "label": "DealerRegistration",
      "regions": [
        {
          "components": [
            {
              "componentAttributes": {
                "background": "background: #FFFFFF",
                "backgroundOverlayColor": "rgba(0, 0, 0, 0.3)",
                "borderBottomColor": "rgba(0, 0, 0, 0.5)",
                "centerAlignLogo": false,
                "collapseNavMenu": false,
                "containHeader": false,
                "containHeaderWidth": 1440,
                "dropdownBackgroundColor": "#FFFFFF",
                "dropdownBackgroundHoverColor": "",
                "dropdownBorderColor": "#F0F0F0",
                "dropdownTextColor": "",
                "dropdownTextHoverColor": "",
                "headerHeight": 16,
                "linkActiveBorderColor": "",
                "linkColor": "rgba(0, 0, 0, 0.8)",
                "linkHoverColor": "rgba(0, 0, 0, 0.7)",
                "linkTextShadowColor": "rgba(255, 255, 255, 0)",
                "logoWidth": 150,
                "searchStyle": "expanded",
                "showAppLauncher": false,
                "showNavMenuOnLeft": true,
                "showNotifications": false,
                "showProfileMenu": false,
                "showSearch": false
              },
              "componentName": "forceCommunity:themeHeaderCompact",
              "id": "00a5e71f-3e0d-49c1-b1a4-8dbf6491b7d6",
              "regions": [
                {
                  "id": "156f9b98-ce6a-4e57-85da-992fc65c7689",
                  "regionName": "themeHeaderProfileMenu",
                  "type": "region"
                },
                {
                  "id": "3daf2432-0e5c-45c5-9dcc-378a9e77eefe",
                  "regionName": "search",
                  "type": "region"
                },
                {
                  "components": [
                    {
                      "componentAttributes": {
                        "navAlignment": "right",
                        "navItemThreshold": 6,
                        "navigationMenuEditorRefresh": "DealerRegistrationMenu"
                      },
                      "componentName": "forceCommunity:themeNav",
                      "id": "645fa080-de36-4f1f-9248-fa4db0d761c2",
                      "renditionMap": {},
                      "type": "component"
                    }
                  ],
                  "id": "b31712cb-21d5-4d0c-b180-8d14d0c8c01d",
                  "regionName": "nav",
                  "type": "region"
                },
                {
                  "id": "bd196507-1d79-4f33-bd36-380e74634c0a",
                  "regionName": "cartIcon",
                  "type": "region"
                }
              ],
              "renditionMap": {},
              "type": "component"
            }
          ],
          "id": "64c67444-17cd-4ea9-ae02-fcd582495d46",
          "regionName": "themeHeader",
          "type": "region"
        },
        {
          "components": [
            {
              "componentAttributes": {
                "bgImage": "background: #FFFFFF url(/sfsites/assets/themes/jepson-background.jpg) top center /cover",
                "bgOverlayColor": "rgba(255, 255, 255, 0.20)",
                "captionText": "Our Mission",
                "captionTextColor": "rgba(0, 0, 0, 0.8)",
                "captionTextShadowColor": "rgba(0, 0, 0, 0)",
                "contentAlignment": "right",
                "contentWidth": 45,
                "ctaBtnOneBgColor": "",
                "ctaBtnOneBgHoverColor": "",
                "ctaBtnOneBorderColor": "rgba(10, 50, 198, 0)",
                "ctaBtnOneOpenNewTab": false,
                "ctaBtnOneText": "Our Projects",
                "ctaBtnOneTextColor": "",
                "ctaBtnOneTextHoverColor": "",
                "ctaBtnOneUrl": "",
                "ctaBtnRadius": 25,
                "ctaBtnTwoBgColor": "rgba(255, 255, 255, 0)",
                "ctaBtnTwoBgHoverColor": "rgba(255, 255, 255, 0.9)",
                "ctaBtnTwoBorderColor": "rgba(0, 0, 0, 0.8)",
                "ctaBtnTwoOpenNewTab": false,
                "ctaBtnTwoText": "Contact Us",
                "ctaBtnTwoTextColor": "rgba(0, 0, 0, 0.8)",
                "ctaBtnTwoTextHoverColor": "rgba(0, 0, 0, 0.8)",
                "ctaBtnTwoUrl": "",
                "ctaShowBtnOne": true,
                "ctaShowBtnTwo": true,
                "fixedHeroWidth": true,
                "heroHeight": 162,
                "heroWidth": 1440,
                "showCaption": true,
                "showSubtitle": true,
                "showTitle": true,
                "subtitleText": "We specialize in the construction of unique and exclusive properties.  We deliver outstanding quality and design for leading architects and private clients around the world.",
                "subtitleTextColor": "rgba(0, 0, 0, 0.8)",
                "subtitleTextShadowColor": "rgba(0, 0, 0, 0)",
                "titleText": "Your Dream Home",
                "titleTextColor": "rgba(0, 0, 0, 0.8)",
                "titleTextShadowColor": "rgba(0, 0, 0, 0)",
                "type": "callToAction"
              },
              "componentName": "forceCommunity:themeHeroStarter",
              "id": "1b57df23-9ae4-480f-b21a-cc9c5e2b6c2d",
              "regions": [
                {
                  "components": [
                    {
                      "componentAttributes": {
                        "backgroundColor": "#FFFFFF",
                        "borderColor": "rgba(0, 0, 0, 0)",
                        "borderRadius": 25,
                        "borderStyle": "outline",
                        "buttonColor": "",
                        "buttonHoverColor": "",
                        "crossObjectTypeaheadApiNames": "",
                        "iconColor": "#FFFFFF",
                        "placeholderText": "Ask a question...",
                        "placeholderTextColor": "rgba(0, 0, 0, 0.6)",
                        "publicDropdownBackgroundColor": "#FFFFFF",
                        "publicDropdownBackgroundHoverColor": "",
                        "publicDropdownBorderColor": "#F0F0F0",
                        "publicDropdownTextColor": "",
                        "publicDropdownTextHoverColor": "",
                        "showSearchButton": true,
                        "textColor": "rgba(0, 0, 0, 0.8)",
                        "typeaheadResultMax": 6,
                        "useTypeahead": true
                      },
                      "componentName": "forceCommunity:themeSearchHero",
                      "id": "846d6df2-0858-41fe-b5d2-ccbf07647596",
                      "renditionMap": {},
                      "type": "component"
                    }
                  ],
                  "id": "0cf4529c-d6ad-4687-a6e6-ad39c3c3f40f",
                  "regionName": "search",
                  "type": "region"
                }
              ],
              "renditionMap": {},
              "type": "component"
            }
          ],
          "id": "147823a1-e720-4cdf-9968-909af5c0970b",
          "regionName": "themeHero",
          "type": "region"
        },
        {
          "id": "5a1f29a2-94fb-4573-a834-110f887450fd",
          "regionName": "themeFooter",
          "type": "region"
        }
      ],
      "type": "view"
    }
  ]
}
